stickler/__init__.py
stickler/action.py
stickler/condition.py
stickler/engine.py
stickler/rule.py
stickler/config/__init__.py
stickler/config/consts.py
stickler/enums/__init__.py
stickler/enums/rule_type_enum.py
stickler/utils/__init__.py
stickler/utils/logger.py
stickler/utils/validator/__init__.py
stickler/utils/validator/base_validator.py
stickler/utils/validator/expression_validator.py
stickler/utils/validator/name_validator.py
stickler/utils/validator/reference_validator.py
stickler/utils/validator/validator_chain.py
tests/__init__.py
tests/conftest.py
tests/test_action.py
tests/test_condition.py
tests/test_engine.py
tests/utils/__init__.py
tests/utils/validator/__init__.py
tests/utils/validator/test_expression_validator.py
tests/utils/validator/test_name_validator.py
tests/utils/validator/test_reference_validator.py
tests/utils/validator/test_validator_chain.py
stickler-1.0.5.dist-info/LICENSE
stickler-1.0.5.dist-info/METADATA
stickler-1.0.5.dist-info/WHEEL
stickler-1.0.5.dist-info/top_level.txt
stickler-1.0.5.dist-info/RECORD
