Metadata-Version: 2.1
Name: stickler
Version: 1.0.5
Summary: PySpark rule engine for data validation and transformation
Home-page: https://github.com/ginacassin/stickler
Author: Gina Cassin
License-File: LICENSE
Requires-Dist: pyspark (>=3.5.0)
Requires-Dist: pydantic (>=2.10.6)
